{
  "id": "gen1_062_hero_shield",
  "name": "Hero Shield",
  "generation": "1",
  "edition": "3rd Edition",
  "rarity": "Common",
  "cardNumber": "062",
  "text": "AL: +4.",
  "effects": [
    {
      "id": "062-E01",
      "trigger": "WHILE_EQUIPPED",
      "condition": {
        "type": "EQUIPPED_TO_CREATURE",
        "text": "Equipped to creature"
      },
      "actionType": "APPLY_STAT_MODIFIER",
      "effectGroup": "Stat Modifier",
      "actionText": "Modify AL",
      "target": "Equipped creature",
      "value": "AL +4",
      "duration": {
        "text": "While equipped",
        "type": "WHILE_EQUIPPED"
      },
      "reusableFunction": "applyStatModifier",
      "params": {
        "target": "Equipped creature",
        "valueText": "AL +4",
        "statChanges": [
          {
            "stat": "AL",
            "operation": "ADD",
            "value": 4,
            "rounding": null
          }
        ],
        "condition": {
          "type": "EQUIPPED_TO_CREATURE",
          "text": "Equipped to creature"
        },
        "duration": {
          "text": "While equipped",
          "type": "WHILE_EQUIPPED"
        },
        "damageType": "",
        "sourceLinked": false,
        "usesAnchoring": false,
        "roundingMode": null,
        "stackRule": null,
        "tickTiming": null
      },
      "notes": "Basic equip modifier. Final AL is capped at 12.",
      "needsReview": false
    }
  ],
  "notes": "",
  "cardType": "MAGIC",
  "magicType": "INFINITE",
  "magicSubType": "EQUIP",
  "isEquip": true
}
